pyrogram/dist/index.js
pyrogram/dist/index.js.map
pyrogram/node_modules/.package-lock.json
pyrogram/node_modules/.bin/acorn
pyrogram/node_modules/.bin/ts-node
pyrogram/node_modules/.bin/ts-node-cwd
pyrogram/node_modules/.bin/ts-node-esm
pyrogram/node_modules/.bin/ts-node-script
pyrogram/node_modules/.bin/ts-node-transpile-only
pyrogram/node_modules/.bin/ts-script
pyrogram/node_modules/.bin/tsc
pyrogram/node_modules/.bin/tsserver
pyrogram/node_modules/@cspotcode/source-map-support/LICENSE.md
pyrogram/node_modules/@cspotcode/source-map-support/README.md
pyrogram/node_modules/@cspotcode/source-map-support/browser-source-map-support.js
pyrogram/node_modules/@cspotcode/source-map-support/package.json
pyrogram/node_modules/@cspotcode/source-map-support/register-hook-require.d.ts
pyrogram/node_modules/@cspotcode/source-map-support/register-hook-require.js
pyrogram/node_modules/@cspotcode/source-map-support/register.d.ts
pyrogram/node_modules/@cspotcode/source-map-support/register.js
pyrogram/node_modules/@cspotcode/source-map-support/source-map-support.d.ts
pyrogram/node_modules/@cspotcode/source-map-support/source-map-support.js
pyrogram/node_modules/@jridgewell/resolve-uri/LICENSE
pyrogram/node_modules/@jridgewell/resolve-uri/README.md
pyrogram/node_modules/@jridgewell/resolve-uri/package.json
pyrogram/node_modules/@jridgewell/resolve-uri/dist/resolve-uri.mjs
pyrogram/node_modules/@jridgewell/resolve-uri/dist/resolve-uri.mjs.map
pyrogram/node_modules/@jridgewell/resolve-uri/dist/resolve-uri.umd.js
pyrogram/node_modules/@jridgewell/resolve-uri/dist/resolve-uri.umd.js.map
pyrogram/node_modules/@jridgewell/resolve-uri/dist/types/resolve-uri.d.ts
pyrogram/node_modules/@jridgewell/sourcemap-codec/LICENSE
pyrogram/node_modules/@jridgewell/sourcemap-codec/README.md
pyrogram/node_modules/@jridgewell/sourcemap-codec/package.json
pyrogram/node_modules/@jridgewell/sourcemap-codec/dist/sourcemap-codec.mjs
AyiinXd-0.1.3.dist-info/LICENSE
AyiinXd-0.1.3.dist-info/METADATA
AyiinXd-0.1.3.dist-info/WHEEL
AyiinXd-0.1.3.dist-info/top_level.txt
AyiinXd-0.1.3.dist-info/RECORD
